README.md
setup.py
seabird_ctd/__init__.py
seabird_ctd/ctd_models.py
seabird_ctd/interrupt.py
seabird_ctd/local_test_settings.py
seabird_ctd/simulated.py
seabird_ctd/tests.py
seabird_ctd/version.py
seabird_ctd.egg-info/PKG-INFO
seabird_ctd.egg-info/SOURCES.txt
seabird_ctd.egg-info/dependency_links.txt
seabird_ctd.egg-info/requires.txt
seabird_ctd.egg-info/top_level.txt