Metadata-Version: 1.1
Name: seabird-ctd
Version: 0.2.4.6
Summary: Tools for communicating with, retrieving data from, and managing a fixed Seabird CTD deployment
Home-page: https://bitbucket.org/b195m/seabird_ctd/
Author: Nick Santos
Author-email: nick@nicksantos.com
License: MIT
Keywords: seabird ctd serial temperature pressure conductivity
Platform: UNKNOWN
Classifier: Development Status :: 4 - Beta
Classifier: Intended Audience :: Developers
Classifier: License :: OSI Approved :: MIT License
Classifier: Programming Language :: Python :: 2
Classifier: Programming Language :: Python :: 2.7
Classifier: Programming Language :: Python :: 3
Classifier: Programming Language :: Python :: 3.5
Classifier: Programming Language :: Python :: 3.6
